setup.cfg
setup.py
forecastiopy/FIOAlerts.py
forecastiopy/FIOCurrently.py
forecastiopy/FIODaily.py
forecastiopy/FIOFlags.py
forecastiopy/FIOHourly.py
forecastiopy/FIOMinutely.py
forecastiopy/ForecastIO.py
forecastiopy/__init__.py
forecastiopy.egg-info/PKG-INFO
forecastiopy.egg-info/SOURCES.txt
forecastiopy.egg-info/dependency_links.txt
forecastiopy.egg-info/requires.txt
forecastiopy.egg-info/top_level.txt
forecastiopy.egg-info/zip-safe