Metadata-Version: 1.1
Name: forecastiopy
Version: 0.3
Summary: A wrapper to access weather data provided by darksky.net
Home-page: http://github.com/dvdme/forecastiopy
Author: David Ervideira
Author-email: david.dme@gmail.com
License: Eclipse Public License
Download-URL: http://github.com/dvdme/forecastiopy/archive/0.3.tar.gz
Keywords: weather,forecastio,forecast.io,rest,darksky,darksky.net
Platform: UNKNOWN
